mlbugdetection/__init__.py
mlbugdetection/analysis_report.py
mlbugdetection/calibration.py
mlbugdetection/critical_values.py
mlbugdetection/load_data.py
mlbugdetection/load_models.py
mlbugdetection/monotonic.py
mlbugdetection/sanity.py
mlbugdetection/data/breast-cancer.csv
mlbugdetection/models/KNNBreastCancer.pkl
mlbugdetection/models/NNBreastCancer.pkl
mlbugdetection-0.0.12.dist-info/LICENSE
mlbugdetection-0.0.12.dist-info/METADATA
mlbugdetection-0.0.12.dist-info/WHEEL
mlbugdetection-0.0.12.dist-info/top_level.txt
mlbugdetection-0.0.12.dist-info/RECORD
