Metadata-Version: 2.1
Name: mlbugdetection
Version: 0.0.12
Summary: A package for identify Machine Learning bugs
Author: João Gianfaldoni | Giovanni Cardoso | William Silva
Author-email: william.silva.ismart@gmail.com
Keywords: python,machine learning,bug detection
Classifier: Development Status :: 3 - Alpha
Classifier: Intended Audience :: Developers
Classifier: Programming Language :: Python :: 3
Classifier: Operating System :: Unix
Classifier: Operating System :: MacOS :: MacOS X
Classifier: Operating System :: Microsoft :: Windows
License-File: LICENSE
Requires-Dist: xgboost
Requires-Dist: numpy
Requires-Dist: pandas
Requires-Dist: ipykernel
Requires-Dist: pytest
Requires-Dist: sklearn
